flowistic_todo-0.2.2.dist-info/licenses/LICENSE
todo/__init__.py
todo/board.py
todo/cli.py
flowistic_todo-0.2.2.dist-info/METADATA
flowistic_todo-0.2.2.dist-info/WHEEL
flowistic_todo-0.2.2.dist-info/entry_points.txt
flowistic_todo-0.2.2.dist-info/top_level.txt
flowistic_todo-0.2.2.dist-info/RECORD
