Metadata-Version: 2.4
Name: flowistic-todo
Version: 0.2.2
Summary: A rich CLI todo app with project management and task tagging
Author-email: Fayssal El Mofatiche <fayssal.elmofatiche@flowistic.ai>
License: MIT
Project-URL: Homepage, https://github.com/flowistic-ai/todo
Project-URL: Repository, https://github.com/flowistic-ai/todo
Keywords: todo,cli,project management
Classifier: Development Status :: 4 - Beta
Classifier: Environment :: Console
Classifier: Intended Audience :: Developers
Classifier: License :: OSI Approved :: MIT License
Classifier: Programming Language :: Python :: 3
Classifier: Programming Language :: Python :: 3.9
Classifier: Programming Language :: Python :: 3.10
Classifier: Topic :: Software Development :: Libraries :: Python Modules
Requires-Python: >=3.9
License-File: LICENSE
Requires-Dist: typer==0.9.0
Requires-Dist: rich==13.7.0
Requires-Dist: pyyaml==6.0.1
Requires-Dist: dateparser==1.2.0
Requires-Dist: python-dateutil>=2.9.0.post0
Requires-Dist: toml>=0.10.2
Requires-Dist: dash>=3.0.4
Requires-Dist: dash-bootstrap-components>=2.0.2
Requires-Dist: dash-mantine-components>=1.2.0
Requires-Dist: pkginfo>=1.12.1.2
Requires-Dist: numpy>=2.0.2
Requires-Dist: pandas>=2.2.3
Requires-Dist: openpyxl>=3.1.5
Dynamic: license-file
